socaity_router/CONSTS.py
socaity_router/__init__.py
socaity_router/settings.py
socaity_router/socaity_router.py
socaity_router/compatibility/__init__.py
socaity_router/compatibility/upload.py
socaity_router/core/JobManager.py
socaity_router/core/__init__.py
socaity_router/core/job/InternalJob.py
socaity_router/core/job/JobProgress.py
socaity_router/core/job/JobResult.py
socaity_router/core/job/__init__.py
socaity_router/core/routers/_SocaityRouter.py
socaity_router/core/routers/__init__.py
socaity_router/core/routers/_fastapi_router.py
socaity_router/core/routers/_runpod_router.py
socaity_router/core/routers/router_mixins/__init__.py
socaity_router/core/routers/router_mixins/_queue_mixin.py
socaity_router-0.0.3.dist-info/LICENSE
socaity_router-0.0.3.dist-info/METADATA
socaity_router-0.0.3.dist-info/WHEEL
socaity_router-0.0.3.dist-info/top_level.txt
socaity_router-0.0.3.dist-info/RECORD
